[
  {
    "regions": [
      "PZ"
    ],
    "playRate": 0.2,
    "matchesCollected": 1,
    "matchesWin": 1
  },
  {
    "regions": [
      "IO"
    ],
    "playRate": 0.3,
    "matchesCollected": 2,
    "matchesWin": 2
  },
  {
    "regions": [
      "DE",
      "NX"
    ],
    "playRate": 0.6,
    "matchesCollected": 4,
    "matchesWin": 3
  },
  {
    "regions": [
      "DE",
      "PZ"
    ],
    "playRate": 1.1,
    "matchesCollected": 7,
    "matchesWin": 5
  },
  {
    "regions": [
      "DE",
      "SI"
    ],
    "playRate": 1.4,
    "matchesCollected": 9,
    "matchesWin": 6
  },
  {
    "regions": [
      "SI"
    ],
    "playRate": 2.4,
    "matchesCollected": 16,
    "matchesWin": 10
  },
  {
    "regions": [
      "BW"
    ],
    "playRate": 0.8,
    "matchesCollected": 5,
    "matchesWin": 3
  },
  {
    "regions": [
      "IO",
      "PZ"
    ],
    "playRate": 4.4,
    "matchesCollected": 29,
    "matchesWin": 17
  },
  {
    "regions": [
      "IO",
      "SI"
    ],
    "playRate": 2.9,
    "matchesCollected": 19,
    "matchesWin": 11
  },
  {
    "regions": [
      "PZ",
      "SI"
    ],
    "playRate": 1.7,
    "matchesCollected": 11,
    "matchesWin": 6
  },
  {
    "regions": [
      "MT"
    ],
    "playRate": 2.3,
    "matchesCollected": 15,
    "matchesWin": 8
  },
  {
    "regions": [
      "MT",
      "NX"
    ],
    "playRate": 0.6,
    "matchesCollected": 4,
    "matchesWin": 0
  },
  {
    "regions": [
      "FR"
    ],
    "playRate": 1.2,
    "matchesCollected": 8,
    "matchesWin": 2
  },
  {
    "regions": [
      "BW",
      "DE"
    ],
    "playRate": 5.9,
    "matchesCollected": 39,
    "matchesWin": 10
  },
  {
    "regions": [
      "BW",
      "IO"
    ],
    "playRate": 1.4,
    "matchesCollected": 9,
    "matchesWin": 3
  },
  {
    "regions": [
      "MT",
      "PZ"
    ],
    "playRate": 3,
    "matchesCollected": 20,
    "matchesWin": 7
  },
  {
    "regions": [
      "BW",
      "NX"
    ],
    "playRate": 22.9,
    "matchesCollected": 152,
    "matchesWin": 55
  },
  {
    "regions": [
      "BW",
      "PZ"
    ],
    "playRate": 3.3,
    "matchesCollected": 22,
    "matchesWin": 8
  },
  {
    "regions": [
      "BW",
      "SI"
    ],
    "playRate": 9,
    "matchesCollected": 60,
    "matchesWin": 22
  },
  {
    "regions": [
      "BW",
      "FR"
    ],
    "playRate": 6.9,
    "matchesCollected": 46,
    "matchesWin": 17
  },
  {
    "regions": [
      "DE",
      "IO"
    ],
    "playRate": 9.5,
    "matchesCollected": 63,
    "matchesWin": 24
  },
  {
    "regions": [
      "NX",
      "SI"
    ],
    "playRate": 6,
    "matchesCollected": 40,
    "matchesWin": 16
  },
  {
    "regions": [
      "FR",
      "PZ"
    ],
    "playRate": 1.5,
    "matchesCollected": 10,
    "matchesWin": 4
  },
  {
    "regions": [
      "BW",
      "MT"
    ],
    "playRate": 0.8,
    "matchesCollected": 5,
    "matchesWin": 2
  },
  {
    "regions": [
      "FR",
      "MT"
    ],
    "playRate": 9.3,
    "matchesCollected": 62,
    "matchesWin": 26
  },
  {
    "regions": [
      "FR",
      "SI"
    ],
    "playRate": 22.700001,
    "matchesCollected": 151,
    "matchesWin": 65
  },
  {
    "regions": [
      "NX",
      "PZ"
    ],
    "playRate": 3.5,
    "matchesCollected": 23,
    "matchesWin": 10
  },
  {
    "regions": [
      "DE",
      "FR"
    ],
    "playRate": 4.7,
    "matchesCollected": 31,
    "matchesWin": 14
  },
  {
    "regions": [
      "DE",
      "MT"
    ],
    "playRate": 13.9,
    "matchesCollected": 92,
    "matchesWin": 42
  },
  {
    "regions": [
      "IO",
      "MT"
    ],
    "playRate": 14.6,
    "matchesCollected": 97,
    "matchesWin": 45
  },
  {
    "regions": [
      "MT",
      "SI"
    ],
    "playRate": 6.5,
    "matchesCollected": 43,
    "matchesWin": 20
  },
  {
    "regions": [
      "IO",
      "NX"
    ],
    "playRate": 6,
    "matchesCollected": 40,
    "matchesWin": 19
  },
  {
    "regions": [
      "FR",
      "NX"
    ],
    "playRate": 6.8,
    "matchesCollected": 45,
    "matchesWin": 22
  },
  {
    "regions": [
      "DE"
    ],
    "playRate": 2.7,
    "matchesCollected": 18,
    "matchesWin": 9
  },
  {
    "regions": [
      "NX"
    ],
    "playRate": 0.3,
    "matchesCollected": 2,
    "matchesWin": 1
  }
]