[
  {
    "regions": [
      "BW",
      "FR"
    ],
    "playRate": 5.3,
    "matchesCollected": 1,
    "matchesWin": 1
  },
  {
    "regions": [
      "DE",
      "NX"
    ],
    "playRate": 10.5,
    "matchesCollected": 2,
    "matchesWin": 2
  },
  {
    "regions": [
      "NX",
      "PZ"
    ],
    "playRate": 5.3,
    "matchesCollected": 1,
    "matchesWin": 1
  },
  {
    "regions": [
      "FR",
      "NX"
    ],
    "playRate": 5.3,
    "matchesCollected": 1,
    "matchesWin": 1
  },
  {
    "regions": [
      "DE",
      "FR"
    ],
    "playRate": 10.5,
    "matchesCollected": 2,
    "matchesWin": 2
  },
  {
    "regions": [
      "FR",
      "SI"
    ],
    "playRate": 15.8,
    "matchesCollected": 3,
    "matchesWin": 2
  },
  {
    "regions": [
      "IO",
      "MT"
    ],
    "playRate": 68.400002,
    "matchesCollected": 13,
    "matchesWin": 7
  },
  {
    "regions": [
      "PZ",
      "SI"
    ],
    "playRate": 5.3,
    "matchesCollected": 1,
    "matchesWin": 0
  },
  {
    "regions": [
      "DE",
      "IO"
    ],
    "playRate": 5.3,
    "matchesCollected": 1,
    "matchesWin": 0
  },
  {
    "regions": [
      "BW",
      "PZ"
    ],
    "playRate": 5.3,
    "matchesCollected": 1,
    "matchesWin": 0
  },
  {
    "regions": [
      "FR",
      "MT"
    ],
    "playRate": 31.6,
    "matchesCollected": 6,
    "matchesWin": 1
  },
  {
    "regions": [
      "MT",
      "PZ"
    ],
    "playRate": 26.299999,
    "matchesCollected": 5,
    "matchesWin": 1
  },
  {
    "regions": [
      "MT",
      "SI"
    ],
    "playRate": 36.799999,
    "matchesCollected": 7,
    "matchesWin": 2
  },
  {
    "regions": [
      "BW",
      "NX"
    ],
    "playRate": 36.799999,
    "matchesCollected": 7,
    "matchesWin": 2
  },
  {
    "regions": [
      "DE",
      "MT"
    ],
    "playRate": 31.6,
    "matchesCollected": 6,
    "matchesWin": 2
  },
  {
    "regions": [
      "BW",
      "DE"
    ],
    "playRate": 10.5,
    "matchesCollected": 2,
    "matchesWin": 1
  },
  {
    "regions": [
      "IO",
      "NX"
    ],
    "playRate": 21.1,
    "matchesCollected": 4,
    "matchesWin": 2
  },
  {
    "regions": [
      "BW",
      "SI"
    ],
    "playRate": 21.1,
    "matchesCollected": 4,
    "matchesWin": 2
  }
]